polars_evm/__init__.py
polars_evm/py.typed
polars_evm/_helpers/__init__.py
polars_evm/_helpers/filtering.py
polars_evm/_helpers/formatting.py
polars_evm/_helpers/hashes.py
polars_evm/_helpers/serde.py
polars_evm/_helpers/conversions/__init__.py
polars_evm/_helpers/conversions/binary_float_conversions.py
polars_evm/_helpers/conversions/binary_hex_conversions.py
polars_evm/_helpers/decoding/__init__.py
polars_evm/_helpers/decoding/decoding_columns.py
polars_evm/_helpers/decoding/decoding_events.py
polars_evm/_helpers/decoding/decoding_transactions.py
polars_evm/_helpers/decoding/decoding_types.py
polars_evm/namespaces/__init__.py
polars_evm/namespaces/df_namespace.py
polars_evm/namespaces/expr_namespace.py
polars_evm/namespaces/lazyframe_namespace.py
polars_evm/namespaces/series_namespace.py
polars_evm-0.2.6.dist-info/LICENSE-APACHE
polars_evm-0.2.6.dist-info/LICENSE-MIT
polars_evm-0.2.6.dist-info/WHEEL
polars_evm-0.2.6.dist-info/METADATA
polars_evm-0.2.6.dist-info/RECORD
