Metadata-Version: 2.1
Name: polars_evm
Version: 0.2.6
Summary: Utilities for working with EVM data in polars
Requires-Python: >=3.7
Requires-Dist: pycryptodome >=3.9.1, <4
Project-URL: Source, https://github.com/sslivkoff/polars_evm
